<root>
	<!--
		   1-100  for Market
		 101-1000 for Bundle Packages
		1001-3000 for Boxes & Chance Packs
		3001-4000 for Special Market
		4001-5000 for Emporium
		5001-6000 for Shard Bundle Packages
		6001-7000 for Reward Boxes
		7001-8000 for Step Boxes

		Boxes get +250 <priority>
	-->

	<event_box>
		<id>6000</id>
		<name>Stub Reward Box</name>
		<desc>test</desc>
		<start_time>1</start_time>
		<end_time>2</end_time>
	</event_box>

	<!-- 6001-6101: Old events removed. See old versions for archive. -->

	<event_box>
		<id>6103</id>
		<name>Elemental Arena Chest</name>
		<desc>Use Arena Coins to pull from a set of Dual ^c0DFFEpic ^cFFFFReward cards or the chance of an Arena Trophy! Each pull also grants Sneggle Stones!</desc>
		<category>1</category>
		<asset_prefab>elemental_arena_box</asset_prefab>
		<background_prefab>arena_box_banner</background_prefab>
		<bundle>76</bundle>
		<priority>-60</priority>
		<show_desc>1</show_desc>
		<cost item="5" num="1000"/>
		<start_index>1</start_index>
		<chance_pack>1</chance_pack>
		<item id="20" order="1"/> <!-- Trophy -->
		<card id="12010" level="1" order="2"/>  <!-- Silver Wind Spirit -->
		<card id="12170" level="1" order="3"/>  <!-- Amberguard Protector -->
		<card id="12238" level="1" order="4"/>  <!-- Flamey, the Bushfire -->
		<bonus_item id="104500" min="1" max="4"/>
	</event_box>

	<event_box>
		<id>6104</id>
		<name>Angel Arena Chest</name>
		<desc>Use Arena Coins to pull from a set of Dual ^c0DFFEpic ^cFFFFReward cards or the chance of an Arena Trophy! Each pull also grants ^cE7FFRasako Stones^cFFFF!</desc>
		<help_desc>Each pull has a 25% chance of granting an Arena Trophy, instead of one of the cards. Each pull also grants between 1-4 Champion Stones!</help_desc>
		<category>1</category>
		<asset_prefab>angel_arena_box</asset_prefab>
		<background_prefab>arena_box_banner</background_prefab>
		<bundle>76</bundle>
		<priority>-60</priority>
		<show_desc>1</show_desc>
		<cost item="5" num="1000"/>
		<start_index>1</start_index>
		<chance_pack>1</chance_pack>
		<item id="20" order="1"/> <!-- Trophy -->
		<card id="12203" level="1" order="2"/>  <!-- Absent Formation -->
		<card id="12219" level="1" order="3"/>  <!-- Freya's Ranger -->
		<card id="12230" level="1" order="4"/>  <!-- Blazing Holyfire -->
		<bonus_item id="104501" min="1" max="4"/>
	</event_box>

</root>